<Properties StartupConfiguration="{BE3A7A51-3CC2-44E7-BCFD-2C4B8F932342}|Default">
  <MultiItemStartupConfigurations />
  <MonoDevelop.Ide.ItemProperties.TelegramBotExperiments PreferredExecutionTarget="MonoDevelop.Default" />
  <MonoDevelop.Ide.Workbench ActiveDocument="TelgramBot/Program.cs">
    <Files>
      <File FileName="TelgramBot/User.cs" IsPinned="True" />
      <File FileName="TelgramBot/Program.cs" Line="81" Column="1" />
      <File FileName="Test/UnitTest1.cs" Line="21" Column="1" />
      <File FileName="TelgramBot/EmptyClass.cs" Line="89" Column="1" />
    </Files>
    <Pads>
      <Pad Id="ProjectPad">
        <State name="__root__">
          <Node name="TelgramBot" expanded="True">
            <Node name="Solution Items" expanded="True" />
            <Node name="TelegramBotExperiments" expanded="True">
              <Node name="Program.cs" selected="True" />
            </Node>
            <Node name="Test" expanded="True" />
          </Node>
        </State>
      </Pad>
      <Pad Id="MonoDevelop.UnitTesting.TestPad">
        <State name="__root__">
          <Node name="TelgramBot" expanded="True" />
        </State>
      </Pad>
    </Pads>
  </MonoDevelop.Ide.Workbench>
  <MonoDevelop.Ide.Workspace ActiveConfiguration="Debug" />
  <MonoDevelop.Ide.DebuggingService.PinnedWatches />
  <MonoDevelop.Ide.DebuggingService.Breakpoints>
    <BreakpointStore />
  </MonoDevelop.Ide.DebuggingService.Breakpoints>
</Properties>